{
    "skills": [
        {
            "id": 0,
            "name": "Overall",
            "rank": 15005,
            "level": 2068,
            "xp": 437840812
        },
        {
            "id": 1,
            "name": "Attack",
            "rank": 75092,
            "level": 90,
            "xp": 5497534
        },
        {
            "id": 2,
            "name": "Defence",
            "rank": 126542,
            "level": 85,
            "xp": 3317247
        },
        {
            "id": 3,
            "name": "Strength",
            "rank": 106445,
            "level": 87,
            "xp": 4175704
        },
        {
            "id": 4,
            "name": "Hitpoints",
            "rank": 10472,
            "level": 99,
            "xp": 86826355
        },
        {
            "id": 5,
            "name": "Ranged",
            "rank": 3467,
            "level": 99,
            "xp": 200000000
        },
        {
            "id": 6,
            "name": "Prayer",
            "rank": 134103,
            "level": 89,
            "xp": 5330027
        },
        {
            "id": 7,
            "name": "Magic",
            "rank": 113751,
            "level": 99,
            "xp": 19639432
        },
        {
            "id": 8,
            "name": "Cooking",
            "rank": 125608,
            "level": 92,
            "xp": 6591386
        },
        {
            "id": 9,
            "name": "Woodcutting",
            "rank": 16806,
            "level": 88,
            "xp": 4731042
        },
        {
            "id": 10,
            "name": "Fletching",
            "rank": 46208,
            "level": 86,
            "xp": 3767732
        },
        {
            "id": 11,
            "name": "Fishing",
            "rank": 156040,
            "level": 83,
            "xp": 2933623
        },
        {
            "id": 12,
            "name": "Firemaking",
            "rank": 23662,
            "level": 85,
            "xp": 3371499
        },
        {
            "id": 13,
            "name": "Crafting",
            "rank": 66002,
            "level": 89,
            "xp": 4940214
        },
        {
            "id": 14,
            "name": "Smithing",
            "rank": 32940,
            "level": 90,
            "xp": 5494023
        },
        {
            "id": 15,
            "name": "Mining",
            "rank": 9890,
            "level": 95,
            "xp": 9322706
        },
        {
            "id": 16,
            "name": "Herblore",
            "rank": 4943,
            "level": 95,
            "xp": 9238398
        },
        {
            "id": 17,
            "name": "Agility",
            "rank": 12714,
            "level": 86,
            "xp": 3924949
        },
        {
            "id": 18,
            "name": "Thieving",
            "rank": 61811,
            "level": 99,
            "xp": 18046740
        },
        {
            "id": 19,
            "name": "Slayer",
            "rank": 3925,
            "level": 99,
            "xp": 28174305
        },
        {
            "id": 20,
            "name": "Farming",
            "rank": 35194,
            "level": 88,
            "xp": 4828618
        },
        {
            "id": 21,
            "name": "Runecraft",
            "rank": 32311,
            "level": 80,
            "xp": 2064636
        },
        {
            "id": 22,
            "name": "Hunter",
            "rank": 54008,
            "level": 80,
            "xp": 2069258
        },
        {
            "id": 23,
            "name": "Construction",
            "rank": 51611,
            "level": 85,
            "xp": 3555384
        }
    ],
    "activities": [
        {
            "id": 0,
            "name": "League Points",
            "rank": 4455,
            "score": 38450
        },
        {
            "id": 1,
            "name": "Deadman Points",
            "rank": -1,
            "score": -1
        },
        {
            "id": 2,
            "name": "Bounty Hunter - Hunter",
            "rank": -1,
            "score": -1
        },
        {
            "id": 3,
            "name": "Bounty Hunter - Rogue",
            "rank": -1,
            "score": -1
        },
        {
            "id": 4,
            "name": "Bounty Hunter (Legacy) - Hunter",
            "rank": -1,
            "score": -1
        },
        {
            "id": 5,
            "name": "Bounty Hunter (Legacy) - Rogue",
            "rank": -1,
            "score": -1
        },
        {
            "id": 6,
            "name": "Clue Scrolls (all)",
            "rank": 34589,
            "score": 247
        },
        {
            "id": 7,
            "name": "Clue Scrolls (beginner)",
            "rank": 34881,
            "score": 80
        },
        {
            "id": 8,
            "name": "Clue Scrolls (easy)",
            "rank": 42328,
            "score": 91
        },
        {
            "id": 9,
            "name": "Clue Scrolls (medium)",
            "rank": 45693,
            "score": 27
        },
        {
            "id": 10,
            "name": "Clue Scrolls (hard)",
            "rank": 56498,
            "score": 22
        },
        {
            "id": 11,
            "name": "Clue Scrolls (elite)",
            "rank": 15199,
            "score": 20
        },
        {
            "id": 12,
            "name": "Clue Scrolls (master)",
            "rank": 15536,
            "score": 7
        },
        {
            "id": 13,
            "name": "LMS - Rank",
            "rank": -1,
            "score": -1
        },
        {
            "id": 14,
            "name": "PvP Arena - Rank",
            "rank": -1,
            "score": -1
        },
        {
            "id": 15,
            "name": "Soul Wars Zeal",
            "rank": 63492,
            "score": 792
        },
        {
            "id": 16,
            "name": "Rifts closed",
            "rank": -1,
            "score": -1
        },
        {
            "id": 17,
            "name": "Colosseum Glory",
            "rank": -1,
            "score": -1
        },
        {
            "id": 18,
            "name": "Abyssal Sire",
            "rank": 12779,
            "score": 15
        },
        {
            "id": 19,
            "name": "Alchemical Hydra",
            "rank": -1,
            "score": -1
        },
        {
            "id": 20,
            "name": "Amoxliatl",
            "rank": -1,
            "score": -1
        },
        {
            "id": 21,
            "name": "Araxxor",
            "rank": 34144,
            "score": 10
        },
        {
            "id": 22,
            "name": "Artio",
            "rank": -1,
            "score": -1
        },
        {
            "id": 23,
            "name": "Barrows Chests",
            "rank": 10220,
            "score": 215
        },
        {
            "id": 24,
            "name": "Bryophyta",
            "rank": 31102,
            "score": 5
        },
        {
            "id": 25,
            "name": "Callisto",
            "rank": -1,
            "score": -1
        },
        {
            "id": 26,
            "name": "Calvar'ion",
            "rank": -1,
            "score": -1
        },
        {
            "id": 27,
            "name": "Cerberus",
            "rank": 12470,
            "score": 47
        },
        {
            "id": 28,
            "name": "Chambers of Xeric",
            "rank": -1,
            "score": -1
        },
        {
            "id": 29,
            "name": "Chambers of Xeric: Challenge Mode",
            "rank": -1,
            "score": -1
        },
        {
            "id": 30,
            "name": "Chaos Elemental",
            "rank": -1,
            "score": -1
        },
        {
            "id": 31,
            "name": "Chaos Fanatic",
            "rank": -1,
            "score": -1
        },
        {
            "id": 32,
            "name": "Commander Zilyana",
            "rank": 483,
            "score": 344
        },
        {
            "id": 33,
            "name": "Corporeal Beast",
            "rank": -1,
            "score": -1
        },
        {
            "id": 34,
            "name": "Crazy Archaeologist",
            "rank": -1,
            "score": -1
        },
        {
            "id": 35,
            "name": "Dagannoth Prime",
            "rank": 1778,
            "score": 100
        },
        {
            "id": 36,
            "name": "Dagannoth Rex",
            "rank": 1720,
            "score": 100
        },
        {
            "id": 37,
            "name": "Dagannoth Supreme",
            "rank": 2273,
            "score": 100
        },
        {
            "id": 38,
            "name": "Deranged Archaeologist",
            "rank": 7624,
            "score": 27
        },
        {
            "id": 39,
            "name": "Duke Sucellus",
            "rank": -1,
            "score": -1
        },
        {
            "id": 40,
            "name": "General Graardor",
            "rank": 3039,
            "score": 196
        },
        {
            "id": 41,
            "name": "Giant Mole",
            "rank": 2791,
            "score": 29
        },
        {
            "id": 42,
            "name": "Grotesque Guardians",
            "rank": 2340,
            "score": 50
        },
        {
            "id": 43,
            "name": "Hespori",
            "rank": -1,
            "score": -1
        },
        {
            "id": 44,
            "name": "Kalphite Queen",
            "rank": -1,
            "score": -1
        },
        {
            "id": 45,
            "name": "King Black Dragon",
            "rank": -1,
            "score": -1
        },
        {
            "id": 46,
            "name": "Kraken",
            "rank": -1,
            "score": -1
        },
        {
            "id": 47,
            "name": "Kree'Arra",
            "rank": 8162,
            "score": 100
        },
        {
            "id": 48,
            "name": "K'ril Tsutsaroth",
            "rank": 122,
            "score": 382
        },
        {
            "id": 49,
            "name": "Lunar Chests",
            "rank": -1,
            "score": -1
        },
        {
            "id": 50,
            "name": "Mimic",
            "rank": -1,
            "score": -1
        },
        {
            "id": 51,
            "name": "Nex",
            "rank": 6146,
            "score": 30
        },
        {
            "id": 52,
            "name": "Nightmare",
            "rank": 7166,
            "score": 9
        },
        {
            "id": 53,
            "name": "Phosani's Nightmare",
            "rank": -1,
            "score": -1
        },
        {
            "id": 54,
            "name": "Obor",
            "rank": 30780,
            "score": 5
        },
        {
            "id": 55,
            "name": "Phantom Muspah",
            "rank": 14108,
            "score": 33
        },
        {
            "id": 56,
            "name": "Sarachnis",
            "rank": -1,
            "score": -1
        },
        {
            "id": 57,
            "name": "Scorpia",
            "rank": -1,
            "score": -1
        },
        {
            "id": 58,
            "name": "Scurrius",
            "rank": 64988,
            "score": 52
        },
        {
            "id": 59,
            "name": "Skotizo",
            "rank": -1,
            "score": -1
        },
        {
            "id": 60,
            "name": "Sol Heredit",
            "rank": -1,
            "score": -1
        },
        {
            "id": 61,
            "name": "Spindel",
            "rank": -1,
            "score": -1
        },
        {
            "id": 62,
            "name": "Tempoross",
            "rank": -1,
            "score": -1
        },
        {
            "id": 63,
            "name": "The Gauntlet",
            "rank": -1,
            "score": -1
        },
        {
            "id": 64,
            "name": "The Corrupted Gauntlet",
            "rank": -1,
            "score": -1
        },
        {
            "id": 65,
            "name": "The Hueycoatl",
            "rank": -1,
            "score": -1
        },
        {
            "id": 66,
            "name": "The Leviathan",
            "rank": -1,
            "score": -1
        },
        {
            "id": 67,
            "name": "The Whisperer",
            "rank": -1,
            "score": -1
        },
        {
            "id": 68,
            "name": "Theatre of Blood",
            "rank": 1730,
            "score": 23
        },
        {
            "id": 69,
            "name": "Theatre of Blood: Hard Mode",
            "rank": -1,
            "score": -1
        },
        {
            "id": 70,
            "name": "Thermonuclear Smoke Devil",
            "rank": -1,
            "score": -1
        },
        {
            "id": 71,
            "name": "Tombs of Amascut",
            "rank": -1,
            "score": -1
        },
        {
            "id": 72,
            "name": "Tombs of Amascut: Expert Mode",
            "rank": -1,
            "score": -1
        },
        {
            "id": 73,
            "name": "TzKal-Zuk",
            "rank": -1,
            "score": -1
        },
        {
            "id": 74,
            "name": "TzTok-Jad",
            "rank": -1,
            "score": -1
        },
        {
            "id": 75,
            "name": "Vardorvis",
            "rank": -1,
            "score": -1
        },
        {
            "id": 76,
            "name": "Venenatis",
            "rank": -1,
            "score": -1
        },
        {
            "id": 77,
            "name": "Vet'ion",
            "rank": -1,
            "score": -1
        },
        {
            "id": 78,
            "name": "Vorkath",
            "rank": 4669,
            "score": 100
        },
        {
            "id": 79,
            "name": "Wintertodt",
            "rank": -1,
            "score": -1
        },
        {
            "id": 80,
            "name": "Zalcano",
            "rank": -1,
            "score": -1
        },
        {
            "id": 81,
            "name": "Zulrah",
            "rank": -1,
            "score": -1
        }
    ]
}